{"name": "World", "children": [{"name": "Australia", "children": [{"name": "Australia", "children": [{"name": "rock", "size": 1}, {"name": "pop", "size": 3}, {"name": "rap", "size": 1}, {"name": "unknown", "size": 2}, {"name": "metal", "size": 3}]}]}, {"name": "Europe", "children": [{"name": "Belgium", "children": [{"name": "electro", "size": 1}]}, {"name": "France", "children": [{"name": "electro", "size": 1}, {"name": "pop", "size": 1}, {"name": "rap", "size": 5}, {"name": "unknown", "size": 1}]}, {"name": "Great Britain", "children": [{"name": "hip hop", "size": 1}, {"name": "rock", "size": 16}, {"name": "folk", "size": 1}, {"name": "jazz", "size": 5}, {"name": "pop", "size": 5}, {"name": "rap", "size": 1}, {"name": "unknown", "size": 6}, {"name": "metal", "size": 4}, {"name": "electro", "size": 2}]}, {"name": "Austria", "children": [{"name": "metal", "size": 1}, {"name": "classic", "size": 1}, {"name": "rock", "size": 2}]}, {"name": "Estonia", "children": [{"name": "folk", "size": 1}, {"name": "pop", "size": 4}]}, {"name": "Finland", "children": [{"name": "unknown", "size": 6}, {"name": "metal", "size": 4}, {"name": "rock", "size": 4}, {"name": "hip hop", "size": 7}]}, {"name": "Spain", "children": [{"name": "metal", "size": 3}, {"name": "pop", "size": 1}]}, {"name": "Germany", "children": [{"name": "hip hop", "size": 3}, {"name": "rock", "size": 5}, {"name": "folk", "size": 1}, {"name": "pop", "size": 6}, {"name": "rap", "size": 1}, {"name": "unknown", "size": 13}, {"name": "metal", "size": 24}, {"name": "electro", "size": 8}]}, {"name": "European", "children": [{"name": "rock", "size": 3}, {"name": "pop", "size": 2}, {"name": "unknown", "size": 1}, {"name": "metal", "size": 3}, {"name": "electro", "size": 1}]}, {"name": "Norway", "children": [{"name": "rock", "size": 1}, {"name": "electro", "size": 7}]}, {"name": "Sweden", "children": [{"name": "metal", "size": 2}, {"name": "electro", "size": 2}, {"name": "pop", "size": 2}]}, {"name": "Czech Republic", "children": [{"name": "soul", "size": 1}]}, {"name": "Poland", "children": [{"name": "hip hop", "size": 1}, {"name": "unknown", "size": 1}]}, {"name": "Italy", "children": [{"name": "rock", "size": 5}, {"name": "unknown", "size": 2}]}, {"name": "Denmark", "children": [{"name": "rock", "size": 1}, {"name": "electro", "size": 1}, {"name": "unknown", "size": 1}, {"name": "metal", "size": 4}]}, {"name": "Faroe Islands", "children": [{"name": "metal", "size": 1}]}, {"name": "Ukraine", "children": [{"name": "unknown", "size": 1}]}]}, {"name": "America", "children": [{"name": "Canada", "children": [{"name": "metal", "size": 2}, {"name": "pop", "size": 1}]}, {"name": "Chile", "children": [{"name": "rock", "size": 2}]}, {"name": "Venezuela", "children": [{"name": "unknown", "size": 1}]}, {"name": "Argentina", "children": [{"name": "rock", "size": 2}, {"name": "unknown", "size": 1}]}, {"name": "United States of America", "children": [{"name": "hip hop", "size": 51}, {"name": "soul", "size": 1}, {"name": "rock", "size": 69}, {"name": "folk", "size": 3}, {"name": "jazz", "size": 4}, {"name": "pop", "size": 34}, {"name": "classic", "size": 2}, {"name": "rap", "size": 3}, {"name": "unknown", "size": 23}, {"name": "metal", "size": 27}, {"name": "electro", "size": 5}]}, {"name": "Brazil", "children": [{"name": "unknown", "size": 2}, {"name": "metal", "size": 3}, {"name": "rap", "size": 2}, {"name": "rock", "size": 3}]}]}, {"name": "unknown", "children": [{"name": "World wide", "children": [{"name": "hip hop", "size": 2}, {"name": "rock", "size": 7}, {"name": "pop", "size": 1}, {"name": "unknown", "size": 7}, {"name": "metal", "size": 3}, {"name": "electro", "size": 1}]}, {"name": "Unknown", "children": [{"name": "hip hop", "size": 20}, {"name": "rock", "size": 77}, {"name": "folk", "size": 13}, {"name": "jazz", "size": 1}, {"name": "pop", "size": 39}, {"name": "rap", "size": 14}, {"name": "classic", "size": 3}, {"name": "unknown", "size": 166}, {"name": "metal", "size": 25}, {"name": "electro", "size": 15}]}]}, {"name": "Africa", "children": [{"name": "South Africa", "children": [{"name": "rock", "size": 1}]}]}, {"name": "Asia", "children": [{"name": "Russia", "children": [{"name": "unknown", "size": 3}]}, {"name": "India", "children": [{"name": "jazz", "size": 1}]}, {"name": "Japan", "children": [{"name": "hip hop", "size": 1}, {"name": "rock", "size": 4}, {"name": "pop", "size": 10}, {"name": "unknown", "size": 2}, {"name": "metal", "size": 1}]}]}]}